{
  "locale": "en",
  "seo": {
    "title": "Most Popular Technical Indicators for Swing Trading",
    "description": "Swing trading focuses on capturing short- to medium-term price movements by identifying market highs and lows. This article explores key technical indicators, like MA, RSI, Stochastic, and EOM, that help traders analyze trends, momentum, and volume for better entry and exit decisions.",
    "noIndex": true,
    "noFollow": true
  },
  "title": "Most Popular Technical Indicators for Swing Trading",
  "type": "Technical Indicators",
  "image": "/image/articles/most-popular-technical-indicators-for-swing-trading/image.png",
  "description": "Swing trading focuses on capturing short- to medium-term price movements by identifying market highs and lows. This article explores key technical indicators, like MA, RSI, Stochastic, and EOM, that help traders analyze trends, momentum, and volume for better entry and exit decisions."
}
